bokku.py
rookie-0.0.1.dist-info/METADATA
rookie-0.0.1.dist-info/RECORD
rookie-0.0.1.dist-info/WHEEL
rookie-0.0.1.dist-info/entry_points.txt
rookie-0.0.1.dist-info/top_level.txt
