Metadata-Version: 2.1
Name: rookie
Version: 0.0.1
Summary: A small PAAS to deploy Flask/Django, Node, PHP and Static HTML sites using GIT, similar to Heroku
Home-page: https://github.com/mardix/bokku/
Author: Mardix
Author-email: mcx2082@gmail.com
License: MIT
Download-URL: https://github.com/mardix/bokku/tarball/master
Keywords: deploy,bokku,flask,gunicorn,django,workers,heroku,firebase,dokku,paas
Platform: any
Classifier: Environment :: Web Environment
Classifier: Intended Audience :: Developers
Classifier: License :: OSI Approved :: BSD License
Classifier: Operating System :: OS Independent
Classifier: Programming Language :: Python
Classifier: Programming Language :: Python :: 2
Classifier: Programming Language :: Python :: 2.6
Classifier: Programming Language :: Python :: 2.7
Classifier: Programming Language :: Python :: 3
Classifier: Programming Language :: Python :: 3.3
Classifier: Programming Language :: Python :: 3.4
Classifier: Topic :: Internet :: WWW/HTTP :: Dynamic Content
Classifier: Topic :: Software Development :: Libraries :: Python Modules
Requires-Dist: virtualenv
Requires-Dist: uwsgi
Requires-Dist: click
